dccli/__init__.py
dccli/cli.py
dccli/constants.py
dccli/error_codes.py
dccli/git_helper.py
dccli/job.py
dccli/user.py
dccli/utils.py
dccli-0.0.12.dist-info/LICENSE
dccli-0.0.12.dist-info/METADATA
dccli-0.0.12.dist-info/WHEEL
dccli-0.0.12.dist-info/entry_points.txt
dccli-0.0.12.dist-info/top_level.txt
dccli-0.0.12.dist-info/RECORD
