Metadata-Version: 2.1
Name: dccli
Version: 0.0.12
Summary: cli for manage job in DeepCluster.io
Home-page: UNKNOWN
Author: YL & SW
Author-email: deepcluster.io@gmail.com
License: UNKNOWN
Platform: UNKNOWN
Classifier: Programming Language :: Python :: 3
Classifier: License :: OSI Approved :: MIT License
Classifier: Operating System :: OS Independent
Requires-Dist: pyyaml
Requires-Dist: requests
Requires-Dist: clint
